rateguard/__init__.py
rateguard/main.py
rateguard/py.typed
rateguard-0.1.3.dist-info/METADATA
rateguard-0.1.3.dist-info/WHEEL
rateguard-0.1.3.dist-info/RECORD
