Metadata-Version: 2.4
Name: rateguard
Version: 0.1.3
Summary: A lightweight Python decorator for thread-safe rate limiting of function calls.
Author-email: Subhranil Sarkar <subhranil2605@gmail.com>
Requires-Python: >=3.11
